cloudwash/__init__.py
cloudwash/cli.py
cloudwash/client.py
cloudwash/config.py
cloudwash/constants.py
cloudwash/logger.py
cloudwash/utils.py
cloudwash/assets/__init__.py
cloudwash/assets/css/__init__.py
cloudwash/assets/css/reporting.css
cloudwash/entities/__init__.py
cloudwash/entities/providers.py
cloudwash/entities/resources/__init__.py
cloudwash/entities/resources/base.py
cloudwash/entities/resources/containers.py
cloudwash/entities/resources/discs.py
cloudwash/entities/resources/images.py
cloudwash/entities/resources/nics.py
cloudwash/entities/resources/ocps.py
cloudwash/entities/resources/pips.py
cloudwash/entities/resources/stacks.py
cloudwash/entities/resources/vms.py
cloudwash/providers/__init__.py
cloudwash/providers/aws.py
cloudwash/providers/azure.py
cloudwash/providers/gce.py
cloudwash/providers/podman.py
cloudwash/providers/vmware.py
cloudwash-2.1.0.dist-info/LICENSE
cloudwash-2.1.0.dist-info/METADATA
cloudwash-2.1.0.dist-info/WHEEL
cloudwash-2.1.0.dist-info/entry_points.txt
cloudwash-2.1.0.dist-info/top_level.txt
cloudwash-2.1.0.dist-info/RECORD
