Metadata-Version: 2.2
Name: cloudwash
Version: 2.1.0
Summary: The cloud resources cleanup utility
Home-page: https://github.com/RedHatQE/cloudwash
Author: Jitendra Yejare
Author-email: jyejare@redhat.com
License: Apache license
Classifier: License :: OSI Approved :: Apache Software License
Classifier: Programming Language :: Python
Classifier: Programming Language :: Python :: 3
Classifier: Programming Language :: Python :: 3.7
Classifier: Programming Language :: Python :: 3.8
Classifier: Operating System :: OS Independent
Classifier: Intended Audience :: Developers
Classifier: Intended Audience :: System Administrators
Classifier: Topic :: Software Development
Classifier: Topic :: Software Development :: Libraries :: Python Modules
Classifier: Topic :: Software Development :: Quality Assurance
Classifier: Topic :: System :: Systems Administration
License-File: LICENSE
Requires-Dist: wrapanapi
Requires-Dist: dynaconf
Requires-Dist: click
Requires-Dist: wget
Requires-Dist: dominate
Provides-Extra: setup
Requires-Dist: setuptools; extra == "setup"
Requires-Dist: setuptools-scm; extra == "setup"
Requires-Dist: wheel; extra == "setup"
Requires-Dist: twine; extra == "setup"
Provides-Extra: dev
Requires-Dist: pre-commit; extra == "dev"
Requires-Dist: flake8; extra == "dev"
